plixel/CsvAnalyser.py
plixel/SheetAnalyser.py
plixel/__init__.py
plixel-0.0.1.dist-info/licenses/LICENCE.md
tests/__init__.py
tests/test_SheetAnalyser.py
tests/verify.py
plixel-0.0.1.dist-info/METADATA
plixel-0.0.1.dist-info/WHEEL
plixel-0.0.1.dist-info/top_level.txt
plixel-0.0.1.dist-info/RECORD
