Metadata-Version: 2.4
Name: plixel
Version: 0.0.1
Summary: A python package for data analysis and visualization
Author: Bonu Krishna Chaitanya
Author-email: Bonu Krishna Chaitanya <bkc14042005@gmail.com>
License-Expression: MIT
Project-URL: Homepage, https://github.com/XChaitanyaX/plixel
Project-URL: Issues, https://github.com/XChaitanyaX/plixel/issues
Classifier: Programming Language :: Python :: 3
Classifier: Operating System :: OS Independent
Requires-Python: >=3.10
License-File: LICENCE.md
Requires-Dist: pandas
Requires-Dist: openpyxl
Requires-Dist: setuptools
Requires-Dist: matplotlib
Requires-Dist: seaborn
Dynamic: author
Dynamic: license-file
Dynamic: requires-dist
